addons_installer/__init__.py
addons_installer/_version.py
addons_installer/addons_installer.py
addons_installer/api.py
addons_installer/cli.py
addons_installer/git_addons.py
addons_installer/git_credential.py
addons_installer/gitman_addons.py
addons_installer/local_addons.py
addons_installer-4.1.1.dist-info/METADATA
addons_installer-4.1.1.dist-info/WHEEL
addons_installer-4.1.1.dist-info/entry_points.txt
addons_installer-4.1.1.dist-info/top_level.txt
addons_installer-4.1.1.dist-info/RECORD
